[
    {
        "标题": "真实的老虎食人案例，流窜2国吃掉400多人，毙后才知它吃人的真相",
        "链接": "http://mp.weixin.qq.com/s?__biz=MzAwNTc0Mzc2Ng==&mid=2651490526&idx=1&sn=2df164f5e977cb225befd8c90ffd03b9"
    },
    {
        "标题": "孙悟空能大闹天宫，放在封神世界的段位有多高？能否挑战三大圣人？",
        "链接": "http://mp.weixin.qq.com/s?__biz=MzAwNTc0Mzc2Ng==&mid=2651490526&idx=2&sn=d6839e40a67e5dfd514bd8363fa5fdbe"
    },
    {
        "标题": "说文解字：“尻”和“凥”怎么读？什么意思？不是你们想的那样",
        "链接": "http://mp.weixin.qq.com/s?__biz=MzAwNTc0Mzc2Ng==&mid=2651490526&idx=3&sn=8b3693172099626a43580d131baa5716"
    },
    {
        "标题": "历史上真实的座山雕什么样子？比电影中凶残百倍，连日本人都拿他没办法",
        "链接": "http://mp.weixin.qq.com/s?__biz=MzAwNTc0Mzc2Ng==&mid=2651490487&idx=1&sn=3df8d89a935fd6f4a7e64e28bf7e2d61"
    },
    {
        "标题": "李渊野心有多大？把他4个儿子名字连起来，你会发现他天大的野心",
        "链接": "http://mp.weixin.qq.com/s?__biz=MzAwNTc0Mzc2Ng==&mid=2651490487&idx=2&sn=1628766d8098eb29729a3b91f69c5286"
    },
    {
        "标题": "石达开被凌迟，妻子临死前，却高喊另一男子名字，清军：此人已死",
        "链接": "http://mp.weixin.qq.com/s?__biz=MzAwNTc0Mzc2Ng==&mid=2651490473&idx=1&sn=6fb48748a226cb7dcfcf1a13a5819c1a"
    },
    {
        "标题": "包拯六十大寿时感叹膝下无子，儿媳突然跪下说：这是您的儿子！",
        "链接": "http://mp.weixin.qq.com/s?__biz=MzAwNTc0Mzc2Ng==&mid=2651490473&idx=2&sn=8e44414959a331eaab3b3b33ddc782a8"
    },
    {
        "标题": "埃及一块轰动世界的石碑，全球学者无人能解，法国小伙用“中文”破译",
        "链接": "http://mp.weixin.qq.com/s?__biz=MzAwNTc0Mzc2Ng==&mid=2651490473&idx=3&sn=ea2745db41d378197f937c66c6f54815"
    },
    {
        "标题": "此人号称神箭手，一拉弓全射偏，敌军一看大笑，仔细一看吓得落荒而逃",
        "链接": "http://mp.weixin.qq.com/s?__biz=MzAwNTc0Mzc2Ng==&mid=2651490450&idx=1&sn=f93edf7d2b4196378d5019b3a7bb7065"
    },
    {
        "标题": "大将军年羹尧被雍正处死后，雍正是怎么对待其妻女的？",
        "链接": "http://mp.weixin.qq.com/s?__biz=MzAwNTc0Mzc2Ng==&mid=2651490450&idx=2&sn=f39e1e49f344455982e8875d03c18ca1"
    },
    {
        "标题": "明朝“白日飞升”事件，十万人目睹之下，女道士幻化在云雾中",
        "链接": "http://mp.weixin.qq.com/s?__biz=MzAwNTc0Mzc2Ng==&mid=2651490436&idx=1&sn=aaeed26ff4e3e37db4cc21decce2cf3b"
    },
    {
        "标题": "相士跪求皇帝不要出宫，皇帝怒斥：回来就斩了你，相士：你回不来了",
        "链接": "http://mp.weixin.qq.com/s?__biz=MzAwNTc0Mzc2Ng==&mid=2651490436&idx=2&sn=7d8e8601ef87f3be617ef097a7f17d1e"
    },
    {
        "标题": "埃及法老的残忍实验，不教说话让两个婴儿长大，会创造出新的语言吗？",
        "链接": "http://mp.weixin.qq.com/s?__biz=MzAwNTc0Mzc2Ng==&mid=2651490417&idx=1&sn=a94230e214028d4835cda95301a853a7"
    },
    {
        "标题": "康熙长子胤禔被软禁府中26年，疯狂与11位王妃生下29个子女",
        "链接": "http://mp.weixin.qq.com/s?__biz=MzAwNTc0Mzc2Ng==&mid=2651490417&idx=2&sn=26c47072096998522548e2f7471b47b5"
    },
    {
        "标题": "皇帝请群臣吃饭，唯独不给丞相筷子，丞相走后，皇帝：此人不能留",
        "链接": "http://mp.weixin.qq.com/s?__biz=MzAwNTc0Mzc2Ng==&mid=2651490390&idx=1&sn=2394ad0da79da44ff43ad551cf800689"
    },
    {
        "标题": "人没有头也能活下来？几个古代被斩首的案例，最真实的死亡体验",
        "链接": "http://mp.weixin.qq.com/s?__biz=MzAwNTc0Mzc2Ng==&mid=2651490390&idx=2&sn=b1ee1a5794e447bb3b9c2af4400c277a"
    },
    {
        "标题": "皇帝要下令处死权臣，大臣得知后急告妻子：快去告发我要谋反",
        "链接": "http://mp.weixin.qq.com/s?__biz=MzAwNTc0Mzc2Ng==&mid=2651490370&idx=1&sn=5252e90357817867db6a6b4d16809901"
    },
    {
        "标题": "唐末男子装瞎三年保命，妻子当面与他人亲热，睁眼时一举雪耻",
        "链接": "http://mp.weixin.qq.com/s?__biz=MzAwNTc0Mzc2Ng==&mid=2651490370&idx=2&sn=3fac6f0b9a6c6cc7c52d3de460823fae"
    },
    {
        "标题": "“兔子不吃窝边草”，下半句更是经典，道出了人性丑陋",
        "链接": "http://mp.weixin.qq.com/s?__biz=MzAwNTc0Mzc2Ng==&mid=2651490370&idx=3&sn=9f0f46ab0775b057b661682d36fd61f1"
    },
    {
        "标题": "他高中状元，慈禧看到名字却说：取消成绩，没想后来灭掉整个清朝",
        "链接": "http://mp.weixin.qq.com/s?__biz=MzAwNTc0Mzc2Ng==&mid=2651490342&idx=1&sn=ea407b7b8f7516832a2e0b09dc2c48e8"
    },
    {
        "标题": "宋江喝下毒酒后才意识到，梁山真正的老大并不是自己，而是另有其人",
        "链接": "http://mp.weixin.qq.com/s?__biz=MzAwNTc0Mzc2Ng==&mid=2651490342&idx=2&sn=bae6841631899f7d9beb3899197b9809"
    },
    {
        "标题": "宋朝最悲惨的公主，被俘后“谷道破裂”而死，悲惨超出想象",
        "链接": "http://mp.weixin.qq.com/s?__biz=MzAwNTc0Mzc2Ng==&mid=2651490342&idx=3&sn=33836458835b28c7f22d0cb48435bc72"
    },
    {
        "标题": "宰相写下“青鹅”两字被斩首，众人不解，武则天一语道破天机！",
        "链接": "http://mp.weixin.qq.com/s?__biz=MzAwNTc0Mzc2Ng==&mid=2651490312&idx=1&sn=034b5637a927fb07696944cf6ff47c48"
    },
    {
        "标题": "玄奘取经后被软禁，圆寂前仅留二字遗言，激励后人千年",
        "链接": "http://mp.weixin.qq.com/s?__biz=MzAwNTc0Mzc2Ng==&mid=2651490312&idx=2&sn=d826232ddc4dc9da8542508d3c1d40c2"
    },
    {
        "标题": "“晨食壮火，午泄残精”，老祖宗的告诫，别不当回事，这样固精气",
        "链接": "http://mp.weixin.qq.com/s?__biz=MzAwNTc0Mzc2Ng==&mid=2651490312&idx=3&sn=a3b5113bd40d483732dada716948b3ea"
    },
    {
        "标题": "爱因斯坦被誉为天才，为何两个孩子都患有精神病？原因其实很简单",
        "链接": "http://mp.weixin.qq.com/s?__biz=MzAwNTc0Mzc2Ng==&mid=2651490278&idx=1&sn=445459f6d4528f4ab0dda8a5eb39bd9f"
    },
    {
        "标题": "曹操杀吕布时，为何要先勒死再斩首示众？难道他怕吕布吗？",
        "链接": "http://mp.weixin.qq.com/s?__biz=MzAwNTc0Mzc2Ng==&mid=2651490278&idx=2&sn=412645a13cf60513765c176e09651282"
    },
    {
        "标题": "准岳父出上联“岳父岳母是父母”，小伙智对下联，你会对吗？",
        "链接": "http://mp.weixin.qq.com/s?__biz=MzAwNTc0Mzc2Ng==&mid=2651490278&idx=3&sn=c18173414777a736a8fae65deaf29333"
    },
    {
        "标题": "皇帝临终前感慨没儿子，太监突然下跪说：陛下，您儿子在冷宫6岁了",
        "链接": "http://mp.weixin.qq.com/s?__biz=MzAwNTc0Mzc2Ng==&mid=2651490244&idx=1&sn=1c156ff023e0279a9b866b6fbbff01df"
    },
    {
        "标题": "成吉思汗屠城无数，但有底线，3类人绝对不杀",
        "链接": "http://mp.weixin.qq.com/s?__biz=MzAwNTc0Mzc2Ng==&mid=2651490244&idx=2&sn=78a9407f090669eea9965e5ab3c68a53"
    },
    {
        "标题": "地球正在进入第6次大灭绝时代，人类将何去何从？",
        "链接": "http://mp.weixin.qq.com/s?__biz=MzAwNTc0Mzc2Ng==&mid=2651490244&idx=3&sn=282f21bf0b7713a0059f9abbf21b694d"
    },
    {
        "标题": "将军上厕所意外发现了一群蚂蚁，下令全军紧急撤离，部队躲过一劫",
        "链接": "http://mp.weixin.qq.com/s?__biz=MzAwNTc0Mzc2Ng==&mid=2651490200&idx=1&sn=6e37966537d70589a612dfb1b4a25d66"
    },
    {
        "标题": "太平天国拥十万女兵，却从不上战场，她们被安排了什么样的任务？",
        "链接": "http://mp.weixin.qq.com/s?__biz=MzAwNTc0Mzc2Ng==&mid=2651490200&idx=2&sn=9db40929367c29223246e0ceb3584110"
    },
    {
        "标题": "他武功盖世曾名震四方，上梁山后从不上阵打仗，宋江也拿他没办法",
        "链接": "http://mp.weixin.qq.com/s?__biz=MzAwNTc0Mzc2Ng==&mid=2651490182&idx=1&sn=4908035fd54051fec6f32d02373ee991"
    },
    {
        "标题": "皇帝偷偷在宰相袍子烧了一个洞，一年后发现洞还在，立马下令：打开国库",
        "链接": "http://mp.weixin.qq.com/s?__biz=MzAwNTc0Mzc2Ng==&mid=2651490182&idx=2&sn=166c0e99286a14881afc00c39197da46"
    },
    {
        "标题": "明朝“奇人”王世宁活到128岁，每天只吃两样食物，现在很少有人吃了",
        "链接": "http://mp.weixin.qq.com/s?__biz=MzAwNTc0Mzc2Ng==&mid=2651490149&idx=1&sn=176e4945957d2743bd49ed5039a05484"
    },
    {
        "标题": "史上武力最高八大猛将排名，没有一个虚构人物，个个武力值惊人",
        "链接": "http://mp.weixin.qq.com/s?__biz=MzAwNTc0Mzc2Ng==&mid=2651490149&idx=2&sn=5e2e743150e6484053f3cfd2e130e139"
    },
    {
        "标题": "《中国古代名将群》第1集直接爆了：孙武建群，赵括踩雷被踢！",
        "链接": "http://mp.weixin.qq.com/s?__biz=MzAwNTc0Mzc2Ng==&mid=2651490124&idx=1&sn=7c837d8d189ebd16f36892588587eb94"
    },
    {
        "标题": "此人做到权臣的巅峰，欲入后宫强娶皇后，皇后：换我女儿可以吗",
        "链接": "http://mp.weixin.qq.com/s?__biz=MzAwNTc0Mzc2Ng==&mid=2651490124&idx=2&sn=7f4aa4be1eb71476fdc473a7c84a77b4"
    },
    {
        "标题": "孩子要随父姓，却不跟母姓，为何会成为社会的“潜规则”？",
        "链接": "http://mp.weixin.qq.com/s?__biz=MzAwNTc0Mzc2Ng==&mid=2651490124&idx=3&sn=b039a908489b00f49c148837bdc41d33"
    },
    {
        "标题": "石达开被凌迟三千多刀，为什么能一声不吭？其实是他叫不出来",
        "链接": "http://mp.weixin.qq.com/s?__biz=MzAwNTc0Mzc2Ng==&mid=2651490059&idx=1&sn=32bfa1edd4e8cd59168e10ceb3767e1a"
    },
    {
        "标题": "千古绝对，不服就来对！上联：鼠无大小皆称老，下联：你来？",
        "链接": "http://mp.weixin.qq.com/s?__biz=MzAwNTc0Mzc2Ng==&mid=2651490059&idx=2&sn=d33e61eef854fa634fd472b844336883"
    },
    {
        "标题": "梁山108将，能拿得出手的只有七位一流高手，一位绝世高手",
        "链接": "http://mp.weixin.qq.com/s?__biz=MzAwNTc0Mzc2Ng==&mid=2651490059&idx=3&sn=48e6270575ba3773fcd0f7c4383d7acd"
    },
    {
        "标题": "为什么古代皇帝大都短命？有六个重要原因，换谁都活不久！",
        "链接": "http://mp.weixin.qq.com/s?__biz=MzAwNTc0Mzc2Ng==&mid=2651490031&idx=1&sn=fe27c3264ca9541a0c33387c01b6c2d3"
    },
    {
        "标题": "西游六大最强天神实力排行，观音菩萨只能垫底，如来佛祖不过排第四",
        "链接": "http://mp.weixin.qq.com/s?__biz=MzAwNTc0Mzc2Ng==&mid=2651490031&idx=2&sn=4cac7846bb86281ca223b8ac5fa8ac8e"
    },
    {
        "标题": "王阳明：面对惹不起的恶人，把握好这一点，便可赢到最后",
        "链接": "http://mp.weixin.qq.com/s?__biz=MzAwNTc0Mzc2Ng==&mid=2651490031&idx=3&sn=d66dbf1853a45fbe4f984d0eb7f42b46"
    },
    {
        "标题": "最惨的飞行员，跳伞挂树上70年无人发现，发现时已成为树的一部分",
        "链接": "http://mp.weixin.qq.com/s?__biz=MzAwNTc0Mzc2Ng==&mid=2651490008&idx=1&sn=6d08e5988fc3db731b0c81c1f19e650a"
    },
    {
        "标题": "黄巢兵败被杀后，数十姬妾沦为虏俘，唐僖宗处置她们的方式令人不齿",
        "链接": "http://mp.weixin.qq.com/s?__biz=MzAwNTc0Mzc2Ng==&mid=2651490008&idx=2&sn=ce3269a6382a8acf21182ec3e9f133e5"
    },
    {
        "标题": "皇帝给75岁老将军送6个绝色美人，众人多年后，赞叹简直太高明",
        "链接": "http://mp.weixin.qq.com/s?__biz=MzAwNTc0Mzc2Ng==&mid=2651489977&idx=1&sn=ccd9c066e76683c66ea92e1d98a49129"
    },
    {
        "标题": "岳飞年薪72000贯，换算现在相当于多少钱？你绝对难以想象",
        "链接": "http://mp.weixin.qq.com/s?__biz=MzAwNTc0Mzc2Ng==&mid=2651489977&idx=2&sn=cd10654402c5219eeacb83097504adc8"
    },
    {
        "标题": "皇帝请弟弟吃饭，倒杯毒酒说：祝弟弟长命千岁，弟弟一个动作保住性命",
        "链接": "http://mp.weixin.qq.com/s?__biz=MzAwNTc0Mzc2Ng==&mid=2651489963&idx=1&sn=b1bfc467d6049b1ca5ed84c293a1baed"
    },
    {
        "标题": "太医给皇帝的宠妃看病，皇帝称三天治不好死罪，太医：一晚就好！",
        "链接": "http://mp.weixin.qq.com/s?__biz=MzAwNTc0Mzc2Ng==&mid=2651489963&idx=2&sn=5cd2373235c03212692487eb8d168f69"
    },
    {
        "标题": "皇帝找算命先生测字，算命先生却坚决不收钱：死人的钱不能要",
        "链接": "http://mp.weixin.qq.com/s?__biz=MzAwNTc0Mzc2Ng==&mid=2651489942&idx=1&sn=dc39e320c3dfd6faae4be028a2bcdba4"
    },
    {
        "标题": "“酷刑之“点天灯”，把人做成灯芯点燃的过程，看后真的触目人心",
        "链接": "http://mp.weixin.qq.com/s?__biz=MzAwNTc0Mzc2Ng==&mid=2651489942&idx=2&sn=9daca7fd4a67ab449063a4c99636ca82"
    },
    {
        "标题": "唐僧成佛后，为何排名比观音还要高，你看排在如来前面的是谁",
        "链接": "http://mp.weixin.qq.com/s?__biz=MzAwNTc0Mzc2Ng==&mid=2651489920&idx=1&sn=5bdf26ad8e94d79f96c37ac0768a7570"
    },
    {
        "标题": "“生命禁区”突然复活，干涸60多年的罗布泊，为何如今碧波荡漾？",
        "链接": "http://mp.weixin.qq.com/s?__biz=MzAwNTc0Mzc2Ng==&mid=2651489920&idx=2&sn=ac9ec4b92cc49d883e891f11551ff829"
    },
    {
        "标题": "为何说一生饭量有数，谁先吃完谁先故？吃饭，吃的其实是你的定数",
        "链接": "http://mp.weixin.qq.com/s?__biz=MzAwNTc0Mzc2Ng==&mid=2651489920&idx=3&sn=14c9c167ed01359a4ed4fad20c9a619b"
    },
    {
        "标题": "6名士兵被活埋六年，为了活命每天强制聊天，最终4人逃出生天",
        "链接": "http://mp.weixin.qq.com/s?__biz=MzAwNTc0Mzc2Ng==&mid=2651489879&idx=1&sn=1658812555f17dad0018d9075eb17883"
    },
    {
        "标题": "诸葛亮临死前点49盏续命灯，不是给自己续命，而是暗藏两大计谋",
        "链接": "http://mp.weixin.qq.com/s?__biz=MzAwNTc0Mzc2Ng==&mid=2651489879&idx=2&sn=e9fbb0c53c197dcdf6f4600617eb6937"
    },
    {
        "标题": "才子拿36个馒头参加殿试，馒头吃完还没交卷，康熙：赐他头名状元",
        "链接": "http://mp.weixin.qq.com/s?__biz=MzAwNTc0Mzc2Ng==&mid=2651489853&idx=1&sn=02f9892af8e9242aaf933255f0a0d955"
    },
    {
        "标题": "电视台直播刘邦专访，观众：谁需要健腹轮，笑到肌肉发达！",
        "链接": "http://mp.weixin.qq.com/s?__biz=MzAwNTc0Mzc2Ng==&mid=2651489853&idx=2&sn=e97900c07562e4c83d01c9432a84e153"
    },
    {
        "标题": "上联“天若有情天亦老”，整个唐朝无人对得上，宋朝酒鬼巧对下联",
        "链接": "http://mp.weixin.qq.com/s?__biz=MzAwNTc0Mzc2Ng==&mid=2651489853&idx=3&sn=07e4aef7c153e8e6bc79df40d56d6c7b"
    },
    {
        "标题": "《水浒传》中最讽刺的4个绰号，名字连起来读，才明白施耐庵的深意",
        "链接": "http://mp.weixin.qq.com/s?__biz=MzAwNTc0Mzc2Ng==&mid=2651489741&idx=1&sn=c7a4fcc29a718117b81692c39d6997cc"
    },
    {
        "标题": "太监回忆珍妃被处死的内幕！他竟说出心里话：她是史上无与伦比的非凡女子！",
        "链接": "http://mp.weixin.qq.com/s?__biz=MzAwNTc0Mzc2Ng==&mid=2651489741&idx=2&sn=0476ec821a179f0e62be072918bfa396"
    },
    {
        "标题": "俗语“一人不进庙，二人不看井，三人不抬木，四人不徒步”，究竟有什么含义？",
        "链接": "http://mp.weixin.qq.com/s?__biz=MzAwNTc0Mzc2Ng==&mid=2651489741&idx=3&sn=88f4e086560ee2b99d26070d5ef4d252"
    },
    {
        "标题": "非洲“杀人湖”一夜夺走1700人生命，将水抽干后，专家在湖底揪出真凶",
        "链接": "http://mp.weixin.qq.com/s?__biz=MzAwNTc0Mzc2Ng==&mid=2651489703&idx=1&sn=9c83ae86aa415a4aff902f5435864dae"
    },
    {
        "标题": "嫪毐到底有什么特异功能？让赵姬如此痴迷，司马迁道出真相",
        "链接": "http://mp.weixin.qq.com/s?__biz=MzAwNTc0Mzc2Ng==&mid=2651489703&idx=2&sn=6c5604e1c926e7d2ec0a9201467dfb10"
    },
    {
        "标题": "大清最残忍的鸿门宴，8大将军满心欢喜赴宴，还没动筷就被砍下人头",
        "链接": "http://mp.weixin.qq.com/s?__biz=MzAwNTc0Mzc2Ng==&mid=2651489678&idx=1&sn=416c7847cb1cde751cb1da006813c89d"
    },
    {
        "标题": "金字塔底下发现神秘“地宫”，下面埋藏着颠覆世界的秘密！",
        "链接": "http://mp.weixin.qq.com/s?__biz=MzAwNTc0Mzc2Ng==&mid=2651489678&idx=2&sn=59ff6adc0b378d1d020594ec6e066fa8"
    },
    {
        "标题": "天庭的四大天门分别是谁在把守？难怪孙悟空只敢闯南天门",
        "链接": "http://mp.weixin.qq.com/s?__biz=MzAwNTc0Mzc2Ng==&mid=2651489678&idx=3&sn=32eed08150ff40821937d892cb33edf1"
    },
    {
        "标题": "慈禧终于得到张春圃，满足了自己的愿望还放他出宫，张春圃：此生永不入宫",
        "链接": "http://mp.weixin.qq.com/s?__biz=MzAwNTc0Mzc2Ng==&mid=2651489654&idx=1&sn=df0494369f356dbe0b99118ef6d452e2"
    },
    {
        "标题": "“邻居两不交，亲戚三不走”，碰到这五种人，远离才是上上策",
        "链接": "http://mp.weixin.qq.com/s?__biz=MzAwNTc0Mzc2Ng==&mid=2651489654&idx=2&sn=a9b7580e002504e930fe6b48a84da952"
    },
    {
        "标题": "这6个三国中常被叫错的名字，有一个常被提起，但大多数人都念错",
        "链接": "http://mp.weixin.qq.com/s?__biz=MzAwNTc0Mzc2Ng==&mid=2651489654&idx=3&sn=f547f4e32c1b3b835ec862bb7e97ed3b"
    },
    {
        "标题": "武松当年连喝十八碗酒，相当于现在喝多少酒？看完终于明白了",
        "链接": "http://mp.weixin.qq.com/s?__biz=MzAwNTc0Mzc2Ng==&mid=2651489625&idx=1&sn=4914c832bc084ff06e5e896bdffa8ec0"
    },
    {
        "标题": "痴呆三十多年，被宦官扶上皇位后，一道圣旨让宦官们吓破了胆",
        "链接": "http://mp.weixin.qq.com/s?__biz=MzAwNTc0Mzc2Ng==&mid=2651489625&idx=2&sn=25b2537d147c51b01e7e6201281e2cbb"
    },
    {
        "标题": "俗语“六十岁莫交言，七十岁莫留宿，八十岁莫问饭”，体现了古人的智慧",
        "链接": "http://mp.weixin.qq.com/s?__biz=MzAwNTc0Mzc2Ng==&mid=2651489625&idx=3&sn=8d56d22e5733309648ebde4ea1815aac"
    },
    {
        "标题": "唐僧的紧箍咒是啥内容？翻译出来就6个字，谁听了都头大",
        "链接": "http://mp.weixin.qq.com/s?__biz=MzAwNTc0Mzc2Ng==&mid=2651489595&idx=1&sn=0d524eb3e3a98f285297ae837fb9bb81"
    },
    {
        "标题": "明末山海关之战有多惨烈，20万大顺军团灭，李自成痛失15位大将",
        "链接": "http://mp.weixin.qq.com/s?__biz=MzAwNTc0Mzc2Ng==&mid=2651489595&idx=2&sn=e66c30ac38ef5cd7a1e0ff5d45948bba"
    },
    {
        "标题": "“大门朝7开，家穷人有祸”，家中大门有何讲究？说得在理吗",
        "链接": "http://mp.weixin.qq.com/s?__biz=MzAwNTc0Mzc2Ng==&mid=2651489595&idx=3&sn=59ebdda8c4004258cae098d4dacf3788"
    },
    {
        "标题": "钱钟书与林徽因恩怨曝光！连杨绛都劝不过来，原因有这三点",
        "链接": "http://mp.weixin.qq.com/s?__biz=MzAwNTc0Mzc2Ng==&mid=2651489563&idx=1&sn=d9fe1f45ff11d62b3c2ad804ba847de9"
    },
    {
        "标题": "岳父出上联“广东广西有东西”，看3个女婿如何对出下联？太有趣了",
        "链接": "http://mp.weixin.qq.com/s?__biz=MzAwNTc0Mzc2Ng==&mid=2651489563&idx=2&sn=4ad76a62f3a9e04184893cbfc75bec35"
    },
    {
        "标题": "中秋月儿圆，中秋节的由来你知道吗？",
        "链接": "http://mp.weixin.qq.com/s?__biz=MzAwNTc0Mzc2Ng==&mid=2651489563&idx=3&sn=e2fcef69b569269149531728134de0c5"
    },
    {
        "标题": "王宝钏当了18天皇后就死了，为啥薛平贵容不下她？细思极恐",
        "链接": "http://mp.weixin.qq.com/s?__biz=MzAwNTc0Mzc2Ng==&mid=2651489537&idx=1&sn=783975482b2cdb5d562985e0a36bf38a"
    },
    {
        "标题": "历史上四个真正的真龙天子，身上真龙之气现身，秦始皇居然排不上号",
        "链接": "http://mp.weixin.qq.com/s?__biz=MzAwNTc0Mzc2Ng==&mid=2651489537&idx=2&sn=7a78809c487fd3feda18eb4cd02c1a9d"
    },
    {
        "标题": "历史上唐僧取经的真实历程，究竟有没有受到女色、权势的迷惑？",
        "链接": "http://mp.weixin.qq.com/s?__biz=MzAwNTc0Mzc2Ng==&mid=2651489537&idx=3&sn=aefd6312f0739570dffdd97e092e173e"
    },
    {
        "标题": "二战最强“装死”影帝，跳伞挂教堂上装死保住一命，没想一挂就是79年",
        "链接": "http://mp.weixin.qq.com/s?__biz=MzAwNTc0Mzc2Ng==&mid=2651489503&idx=1&sn=ef9aacbb99ba30d9c6c8638e7919509e"
    },
    {
        "标题": "朱允炆逃亡时发现朱元璋密旨，崩溃大呼：早拿出来，朱棣必败无疑！",
        "链接": "http://mp.weixin.qq.com/s?__biz=MzAwNTc0Mzc2Ng==&mid=2651489503&idx=2&sn=9358d7dcbde4922ff5fda09f9d38d661"
    },
    {
        "标题": "6岁女童给公主伴读，却被皇帝一眼相中，执掌后宫长达54年",
        "链接": "http://mp.weixin.qq.com/s?__biz=MzAwNTc0Mzc2Ng==&mid=2651489503&idx=3&sn=f68d5a3ab66738a51f5a266c8772a9e6"
    },
    {
        "标题": "宠妃生出“怪胎”，乾隆：抱出去埋了，皇后道出9字，乾隆立刻放过",
        "链接": "http://mp.weixin.qq.com/s?__biz=MzAwNTc0Mzc2Ng==&mid=2651489481&idx=1&sn=d1dc48489bff0534793ab3d374d94d2e"
    },
    {
        "标题": "当代中国人生活图鉴",
        "链接": "http://mp.weixin.qq.com/s?__biz=MzAwNTc0Mzc2Ng==&mid=2651489481&idx=2&sn=72ac3eb36e8876571c1510e7d18fbe6a"
    },
    {
        "标题": "未来怎么养老，五六十岁的你必看，未来养老必过的三大坎是什么？",
        "链接": "http://mp.weixin.qq.com/s?__biz=MzAwNTc0Mzc2Ng==&mid=2651489481&idx=3&sn=62c16f339717ac509b8ce0b58ddc58ea"
    },
    {
        "标题": "皇帝准备要杀大将，大将知道后对部下说：将士们皇上要杀你们",
        "链接": "http://mp.weixin.qq.com/s?__biz=MzAwNTc0Mzc2Ng==&mid=2651489339&idx=1&sn=628a241561f034601ef439fdf7e083f6"
    },
    {
        "标题": "比干被挖心后，忘了姜子牙的嘱咐，路遇卖菜大妈一开口命丧黄泉",
        "链接": "http://mp.weixin.qq.com/s?__biz=MzAwNTc0Mzc2Ng==&mid=2651489339&idx=2&sn=490c39878b86b8844f0431a99ebe9447"
    },
    {
        "标题": "为何我们自称“汉人”千年？而不是先一统中国的“秦人”",
        "链接": "http://mp.weixin.qq.com/s?__biz=MzAwNTc0Mzc2Ng==&mid=2651489339&idx=3&sn=7b3c24f92d01105018f7cbf571b1ab94"
    },
    {
        "标题": "慈禧太后身染怪病，众太医束手无策，不料被江湖郎中以蚂蟥神奇治愈",
        "链接": "http://mp.weixin.qq.com/s?__biz=MzAwNTc0Mzc2Ng==&mid=2651489308&idx=1&sn=022bab9ecd729d4989154ad02a0f67fe"
    },
    {
        "标题": "御前侍卫虎口救乾隆，乾隆问他要何赏赐？侍卫：我只要一个胖宫女",
        "链接": "http://mp.weixin.qq.com/s?__biz=MzAwNTc0Mzc2Ng==&mid=2651489308&idx=2&sn=73034a25349443874f8cc7f8ed1caa2d"
    },
    {
        "标题": "史上最懒的一位诗人，一生只写了2句诗，却流传至今，人人皆知",
        "链接": "http://mp.weixin.qq.com/s?__biz=MzAwNTc0Mzc2Ng==&mid=2651489308&idx=3&sn=2c50a4d40935794437db9076d0b6194d"
    },
    {
        "标题": "女子挑着两个孩子逃难，相士一见惊呼：你挑着两条龙，后来果然应验",
        "链接": "http://mp.weixin.qq.com/s?__biz=MzAwNTc0Mzc2Ng==&mid=2651489281&idx=1&sn=c9fd67cf3a69d62c586bc1d218b77296"
    },
    {
        "标题": "军统最美女特工“裙带花”，为毛人凤生下8个孩子，竟被丈夫送进疯人院",
        "链接": "http://mp.weixin.qq.com/s?__biz=MzAwNTc0Mzc2Ng==&mid=2651489281&idx=2&sn=5426240925cbc6e98933d394fd4ed9d2"
    },
    {
        "标题": "赵匡胤黄袍加身后，是如何对待柴荣如花似玉的妻子的？",
        "链接": "http://mp.weixin.qq.com/s?__biz=MzAwNTc0Mzc2Ng==&mid=2651489281&idx=3&sn=f57ada43dc497031ae9bc39b7e1ca11b"
    },
    {
        "标题": "单雄信宁死不降李唐，临行刑前，程咬金预言一语成谶，此仇单家来世必报！",
        "链接": "http://mp.weixin.qq.com/s?__biz=MzAwNTc0Mzc2Ng==&mid=2651489264&idx=1&sn=e40b1f89010aaff6690945551dc8f0af"
    },
    {
        "标题": "士兵被活埋9年后奇迹生还，被救出时生龙活虎，只想去找心爱的姑娘",
        "链接": "http://mp.weixin.qq.com/s?__biz=MzAwNTc0Mzc2Ng==&mid=2651489264&idx=2&sn=54cefff868e2e5f46aed46aee2b1ea50"
    },
    {
        "标题": "祖孙三代娶同一女人，原本以为是个故事，没想到却是真实的历史",
        "链接": "http://mp.weixin.qq.com/s?__biz=MzAwNTc0Mzc2Ng==&mid=2651489264&idx=3&sn=34522a36aa0a809eb774a319df674476"
    },
    {
        "标题": "回族人不吃猪肉，满族人不吃狗肉，那汉族不吃什么？有多少人忘记了",
        "链接": "http://mp.weixin.qq.com/s?__biz=MzAwNTc0Mzc2Ng==&mid=2651489229&idx=1&sn=c6c08a2a6edbcf84212efec0e87ae883"
    },
    {
        "标题": "我国一座3000年未改名的城市，只因出过一美人，一说名字家喻户晓",
        "链接": "http://mp.weixin.qq.com/s?__biz=MzAwNTc0Mzc2Ng==&mid=2651489229&idx=2&sn=0cdc4bb658d8726d43e11a6655089443"
    },
    {
        "标题": "“宁遭桃花劫，勿近白虎身”，这里的“白虎”是何物？",
        "链接": "http://mp.weixin.qq.com/s?__biz=MzAwNTc0Mzc2Ng==&mid=2651489229&idx=3&sn=7bf31c34299d67c054bb422da9572f82"
    },
    {
        "标题": "死囚将被处决，朱元璋问：你姓什么？死囚回答后，朱元璋：他可免死5次",
        "链接": "http://mp.weixin.qq.com/s?__biz=MzAwNTc0Mzc2Ng==&mid=2651489202&idx=1&sn=7789820f1a904d1777fdc330534269f8"
    },
    {
        "标题": "亚洲最性感的女神，迷倒1000多个男人，真实身份却是间谍",
        "链接": "http://mp.weixin.qq.com/s?__biz=MzAwNTc0Mzc2Ng==&mid=2651489202&idx=2&sn=e5130be1a037f4a7d79f4c8b21529d00"
    },
    {
        "标题": "如来佛祖为何要送给太上老君十八座金山，真不是买路这么简单",
        "链接": "http://mp.weixin.qq.com/s?__biz=MzAwNTc0Mzc2Ng==&mid=2651489202&idx=3&sn=4584fa2abc816c23a19b46e5ba9b0092"
    },
    {
        "标题": "俗语说“男不带天，女不带仙”，是什么意思？有何讲究？",
        "链接": "http://mp.weixin.qq.com/s?__biz=MzAwNTc0Mzc2Ng==&mid=2651489202&idx=4&sn=7b4a6782eacd275764ed7b9246d1183c"
    },
    {
        "标题": "重庆为啥子出美女？因为历史上的8次大混血，想不出美女都难",
        "链接": "http://mp.weixin.qq.com/s?__biz=MzAwNTc0Mzc2Ng==&mid=2651489180&idx=1&sn=331e731ebf0505d1872b828e2e6c5e90"
    },
    {
        "标题": "李白被妻子嫌弃，写下一首“爽诗”解气，最后14字被无数人当成座右铭",
        "链接": "http://mp.weixin.qq.com/s?__biz=MzAwNTc0Mzc2Ng==&mid=2651489180&idx=2&sn=d35c16488e97f92e90874788ad041225"
    },
    {
        "标题": "明朝共16位皇帝，把他们的名字连起来，你会发现一个神奇的规律",
        "链接": "http://mp.weixin.qq.com/s?__biz=MzAwNTc0Mzc2Ng==&mid=2651489180&idx=3&sn=fd0443d787caf5a0c08b725bff16a63f"
    },
    {
        "标题": "皇后与男子有染，皇帝被气死，遗诏：后宫三千除外，皇后陪葬！",
        "链接": "http://mp.weixin.qq.com/s?__biz=MzAwNTc0Mzc2Ng==&mid=2651489180&idx=4&sn=0439b4b31b7344eed97801f8fc7acc16"
    },
    {
        "标题": "老版《封神榜》里大家都穿得这么暴露？历史上就该这么穿",
        "链接": "http://mp.weixin.qq.com/s?__biz=MzAwNTc0Mzc2Ng==&mid=2651489129&idx=1&sn=c5f53cf921edc092526bcaaf66734696"
    },
    {
        "标题": "朱元璋给朱棣剥橘子吃，马皇后却大惊失色：你父皇想杀你，快跑！",
        "链接": "http://mp.weixin.qq.com/s?__biz=MzAwNTc0Mzc2Ng==&mid=2651489129&idx=2&sn=6a4b425d176b41c0930cfe43ac923efe"
    },
    {
        "标题": "李世民前世究竟是谁？吓得阎王跪拜迎接，连玉皇大帝都礼让三分",
        "链接": "http://mp.weixin.qq.com/s?__biz=MzAwNTc0Mzc2Ng==&mid=2651489129&idx=3&sn=c1dbce2a8a2ce91500ad534999916d6e"
    },
    {
        "标题": "朱元璋到寺庙拜佛，问：我用跪么？方丈八个字救了全寺性命",
        "链接": "http://mp.weixin.qq.com/s?__biz=MzAwNTc0Mzc2Ng==&mid=2651489089&idx=1&sn=61715846b42c7edaf98c22b27fd9ff94"
    },
    {
        "标题": "清朝最后一位格格，隐姓埋名活到2014年，死前含泪说出了皇家丑闻",
        "链接": "http://mp.weixin.qq.com/s?__biz=MzAwNTc0Mzc2Ng==&mid=2651489089&idx=2&sn=2d17952c12091b079aca8fb4738cf4a9"
    },
    {
        "标题": "丈夫出上联：“抱貂蝉，遇贵妃，问昭君，想西施”，妻子的下联绝了",
        "链接": "http://mp.weixin.qq.com/s?__biz=MzAwNTc0Mzc2Ng==&mid=2651489089&idx=3&sn=bd78827b895c0f93668af465df826fe6"
    },
    {
        "标题": "如果把中国古代名将都放在一个群里，他们会聊些什么",
        "链接": "http://mp.weixin.qq.com/s?__biz=MzAwNTc0Mzc2Ng==&mid=2651489088&idx=1&sn=b72936e2ce41080773a5ff3412dd84ab"
    },
    {
        "标题": "因名字太过高雅，被校长嫌弃，她改了个土名字，结果成家喻户晓的女星",
        "链接": "http://mp.weixin.qq.com/s?__biz=MzAwNTc0Mzc2Ng==&mid=2651489088&idx=2&sn=cc9df57b3b85144ff214fe30f1d1dab5"
    },
    {
        "标题": "刘伯温临死前对儿子说：刘家九世之后，必出一奇才，重振刘家，句句应验",
        "链接": "http://mp.weixin.qq.com/s?__biz=MzAwNTc0Mzc2Ng==&mid=2651489088&idx=3&sn=07d57ce9a7daa891d9a95bb751121964"
    },
    {
        "标题": "兵部尚书过家门而不入，宰相：不好，他要起兵谋反，后来果真应验",
        "链接": "http://mp.weixin.qq.com/s?__biz=MzAwNTc0Mzc2Ng==&mid=2651488995&idx=1&sn=d94de7b86ac4f4cb1adf485ae9c736fb"
    },
    {
        "标题": "中国最后一个湘西王，和藏族妻子的一段传奇生死恋",
        "链接": "http://mp.weixin.qq.com/s?__biz=MzAwNTc0Mzc2Ng==&mid=2651488995&idx=2&sn=7adff9509ced9aca925347b70c673a67"
    },
    {
        "标题": "为什么世界上最动人的情话，多是薄情负心汉说的",
        "链接": "http://mp.weixin.qq.com/s?__biz=MzAwNTc0Mzc2Ng==&mid=2651488995&idx=3&sn=e7ef12a181e96b5675fab5fb217692a1"
    },
    {
        "标题": "白骨精之所以自称白骨夫人，那她一定有丈夫，她的丈夫到底是谁？",
        "链接": "http://mp.weixin.qq.com/s?__biz=MzAwNTc0Mzc2Ng==&mid=2651488964&idx=1&sn=6ed1ac8f816a1fddabb19a37bb71b20d"
    },
    {
        "标题": "为什么古人宁愿穷死也不娶“生妻”？",
        "链接": "http://mp.weixin.qq.com/s?__biz=MzAwNTc0Mzc2Ng==&mid=2651488964&idx=2&sn=94bcf293db9bf7fb8dece9128afa17ff"
    },
    {
        "标题": "霍元甲和慈禧保镖比武，为何踢了两脚后，保镖的一句话让他不敢动",
        "链接": "http://mp.weixin.qq.com/s?__biz=MzAwNTc0Mzc2Ng==&mid=2651488964&idx=3&sn=a2af2346a75eb09e879e639cd037877e"
    },
    {
        "标题": "为什么新疆女子很少嫁到内地？当地姑娘说了大实话，内地男性沉默了",
        "链接": "http://mp.weixin.qq.com/s?__biz=MzAwNTc0Mzc2Ng==&mid=2651488950&idx=1&sn=c4fe6c5104ce5cb95110152fdec0ffb1"
    },
    {
        "标题": "广东人喊你出来喝酒",
        "链接": "http://mp.weixin.qq.com/s?__biz=MzAwNTc0Mzc2Ng==&mid=2651488950&idx=2&sn=45718a8091f8ca7c1da9561a1d9b34a7"
    },
    {
        "标题": "周文王拉车800步，周朝天下800年，其实他犯了一个致命错误",
        "链接": "http://mp.weixin.qq.com/s?__biz=MzAwNTc0Mzc2Ng==&mid=2651488950&idx=3&sn=9b2098b465c6173a0b20de6e2af45473"
    },
    {
        "标题": "清朝女子难产昏厥，误认死亡与丈夫合葬，棺木打开专家吓到腿软",
        "链接": "http://mp.weixin.qq.com/s?__biz=MzAwNTc0Mzc2Ng==&mid=2651488892&idx=1&sn=8f441b16bb7c6947ec8cd7bdd88eebac"
    },
    {
        "标题": "老祖宗说“三十如狼，四十如虎”到底是什么意思？你理解对了吗？",
        "链接": "http://mp.weixin.qq.com/s?__biz=MzAwNTc0Mzc2Ng==&mid=2651488892&idx=2&sn=3a02114c98d4f32365e0bfcfe01140d0"
    },
    {
        "标题": "李渊的野心有多大？把他4个儿子名字连起来，你会发现他天大的野心",
        "链接": "http://mp.weixin.qq.com/s?__biz=MzAwNTc0Mzc2Ng==&mid=2651488892&idx=3&sn=e2f3553af0c14f5e413d597b54710bc2"
    },
    {
        "标题": "一个街头卖艺歌女，二婚竟然嫁给皇帝，除了武则天只有她敢穿龙袍",
        "链接": "http://mp.weixin.qq.com/s?__biz=MzAwNTc0Mzc2Ng==&mid=2651488868&idx=1&sn=4b7e88924ed51a855bbe2129220e3f14"
    },
    {
        "标题": "为什么说“男不入川，女不入藏，老不入广”，背后的考虑很真实",
        "链接": "http://mp.weixin.qq.com/s?__biz=MzAwNTc0Mzc2Ng==&mid=2651488868&idx=2&sn=1dcf359f4ea684c382c1adbe4d14f36d"
    },
    {
        "标题": "夫妻之间，如果不再愿意共用这3样东西，多半意味着不爱了",
        "链接": "http://mp.weixin.qq.com/s?__biz=MzAwNTc0Mzc2Ng==&mid=2651488868&idx=3&sn=cc03a5f4a38b1d3976b8504d32a133d9"
    },
    {
        "标题": "为何孙悟空死活也要打死6个盗贼？把6人名字连起来读，就明白了",
        "链接": "http://mp.weixin.qq.com/s?__biz=MzAwNTc0Mzc2Ng==&mid=2651488835&idx=1&sn=18dc1ad6d6834a13abad6cb7dfab49f5"
    },
    {
        "标题": "糊涂大臣替皇帝传话，一言不发就返回：我忘词了！皇帝：此人可用",
        "链接": "http://mp.weixin.qq.com/s?__biz=MzAwNTc0Mzc2Ng==&mid=2651488835&idx=2&sn=3959e575cdf498092d53f0b9bf003d31"
    },
    {
        "标题": "就算再穷，50岁后必须给子女留下这三样东西，才是远见！",
        "链接": "http://mp.weixin.qq.com/s?__biz=MzAwNTc0Mzc2Ng==&mid=2651488835&idx=3&sn=0cbef23ddaaded024bd7bbbce61ab760"
    },
    {
        "标题": "下旨绞杀九岁男童，乾隆皇帝因何连这么一个小孩子都容不下",
        "链接": "http://mp.weixin.qq.com/s?__biz=MzAwNTc0Mzc2Ng==&mid=2651488807&idx=1&sn=40382c68821617245e5dbd68d8be8fb3"
    },
    {
        "标题": "荒野丛林暗藏凶猛食人狮，进化成无鬃毛，专门袭击附近的工人",
        "链接": "http://mp.weixin.qq.com/s?__biz=MzAwNTc0Mzc2Ng==&mid=2651488807&idx=2&sn=6814e77b669e5de3eaada4a5cfb11e71"
    },
    {
        "标题": "连孙权都想盗的赵佗墓，为何两千多年没有被盗？",
        "链接": "http://mp.weixin.qq.com/s?__biz=MzAwNTc0Mzc2Ng==&mid=2651488807&idx=3&sn=1a88afffaad845e99dc6b6374433a91e"
    },
    {
        "标题": "艳妃侮辱蒙古人体臭，后被成吉思汗俘获，躺其怀里却说：大汗真香",
        "链接": "http://mp.weixin.qq.com/s?__biz=MzAwNTc0Mzc2Ng==&mid=2651488766&idx=1&sn=ebc816c612075e5bb26dfe423db32304"
    },
    {
        "标题": "封神榜十大最强天神排名，女娲娘娘仅排第二，鸿钧老祖争议颇大",
        "链接": "http://mp.weixin.qq.com/s?__biz=MzAwNTc0Mzc2Ng==&mid=2651488766&idx=2&sn=166f6ffc36dedd6befe1dfbc018af675"
    },
    {
        "标题": "男人的内裤到底有多野！",
        "链接": "http://mp.weixin.qq.com/s?__biz=MzAwNTc0Mzc2Ng==&mid=2651488766&idx=3&sn=1eb286278c07e2c37cdf9d6a7d7ac9af"
    },
    {
        "标题": "太平天国从不纳粮征税，却可以抵抗清军14年，太平军粮草从何而来",
        "链接": "http://mp.weixin.qq.com/s?__biz=MzAwNTc0Mzc2Ng==&mid=2651488722&idx=1&sn=4c6bfc82a7a27253815df1146029df8a"
    },
    {
        "标题": "古代买一个丫环要多少钱？13岁的最便宜，长大后还能收做小妾",
        "链接": "http://mp.weixin.qq.com/s?__biz=MzAwNTc0Mzc2Ng==&mid=2651488722&idx=2&sn=fd69ebeafe8827cc3643d8d182a7329c"
    },
    {
        "标题": "日本人为什么无法接受日本沉没？",
        "链接": "http://mp.weixin.qq.com/s?__biz=MzAwNTc0Mzc2Ng==&mid=2651488722&idx=3&sn=57ab78f28779e680f16bedd573878cbe"
    },
    {
        "标题": "在希特勒的计划中，如果顺利击败苏联，他的下一个目标是谁",
        "链接": "http://mp.weixin.qq.com/s?__biz=MzAwNTc0Mzc2Ng==&mid=2651488709&idx=1&sn=c83fad2e63bdd209991e6f7dde6c6254"
    },
    {
        "标题": "官员瞧不起一老头问：你有何官职？老头八字回应，官员羞愧难当",
        "链接": "http://mp.weixin.qq.com/s?__biz=MzAwNTc0Mzc2Ng==&mid=2651488709&idx=2&sn=bf0f7ab027630324526955c2803b0148"
    },
    {
        "标题": "它被引进时只是一种马饲料，中国人却将它吃成了一道菜",
        "链接": "http://mp.weixin.qq.com/s?__biz=MzAwNTc0Mzc2Ng==&mid=2651488709&idx=3&sn=e7aa4a0b5e40ac721b00ffb81c7cd2e3"
    },
    {
        "标题": "为什么观音给唐僧，找3个犯过错的徒弟？把名字连起读就知道了",
        "链接": "http://mp.weixin.qq.com/s?__biz=MzAwNTc0Mzc2Ng==&mid=2651488691&idx=1&sn=bed48c7472c1b0cb736310a43bfa0629"
    },
    {
        "标题": "如果刘备夺得天下，会最先杀死这三人，诸葛亮看破不说破",
        "链接": "http://mp.weixin.qq.com/s?__biz=MzAwNTc0Mzc2Ng==&mid=2651488691&idx=2&sn=433a47c20a50b8a5225dcbc6dbb5aa5c"
    },
    {
        "标题": "同样是押送流放的犯人，官差为何争着押送女囚，因为有三个好处",
        "链接": "http://mp.weixin.qq.com/s?__biz=MzAwNTc0Mzc2Ng==&mid=2651488691&idx=3&sn=603b416ae55e144aa2fb09adb605bd9b"
    },
    {
        "标题": "刘罗锅下棋赢了乾隆，乾隆怒斥：不怕朕把你斩了？刘用一句话保住性命",
        "链接": "http://mp.weixin.qq.com/s?__biz=MzAwNTc0Mzc2Ng==&mid=2651488665&idx=1&sn=f253fa41046cce0ae74598498d86e7e3"
    },
    {
        "标题": "黄蓉临终才恍然大悟，出卖郭靖的人，竟是觊觎我美色的身边人",
        "链接": "http://mp.weixin.qq.com/s?__biz=MzAwNTc0Mzc2Ng==&mid=2651488665&idx=2&sn=0769afffdd2a1b866fce21cc492bf955"
    },
    {
        "标题": "朱元璋问女子：天下什么最大？女子回答4个字，却被逼嫁人",
        "链接": "http://mp.weixin.qq.com/s?__biz=MzAwNTc0Mzc2Ng==&mid=2651488610&idx=1&sn=9ad6ded445a54cb66dfda433c8835995"
    },
    {
        "标题": "匈奴、契丹、柔然、突厥、鞑靼、女真，究竟啥意思？终于搞明白了",
        "链接": "http://mp.weixin.qq.com/s?__biz=MzAwNTc0Mzc2Ng==&mid=2651488610&idx=2&sn=a891bc43b9716667bc353df4cc13e3e0"
    },
    {
        "标题": "17岁千金嫁54岁老将，怀孕16次为夫生下6女，晚年坚称：不后悔！",
        "链接": "http://mp.weixin.qq.com/s?__biz=MzAwNTc0Mzc2Ng==&mid=2651488602&idx=1&sn=11fee4378460104319c40837453a4448"
    },
    {
        "标题": "乾隆出一上联：鼠无大小皆称老，纪晓岚对出的下联堪称千古绝对",
        "链接": "http://mp.weixin.qq.com/s?__biz=MzAwNTc0Mzc2Ng==&mid=2651488602&idx=3&sn=9c032e137a9d4a419ff8c32a90afaa16"
    },
    {
        "标题": "宋朝一女婴，出生时不哭不笑，父亲带到寺庙祈福，高僧怒斥：你不该来这里",
        "链接": "http://mp.weixin.qq.com/s?__biz=MzAwNTc0Mzc2Ng==&mid=2651488593&idx=1&sn=f4f16b998e73676befb6bdb876368b61"
    },
    {
        "标题": "黄蓉为何讨厌杨过？你看她与杨过抱在一起时想到了什么",
        "链接": "http://mp.weixin.qq.com/s?__biz=MzAwNTc0Mzc2Ng==&mid=2651488593&idx=3&sn=a006daee0a258441fa5f68e07a616734"
    },
    {
        "标题": "家里太穷娶不起老婆，妹妹嫁给哥哥后，生下一孩子家喻户晓",
        "链接": "http://mp.weixin.qq.com/s?__biz=MzAwNTc0Mzc2Ng==&mid=2651488525&idx=1&sn=d5ab18e24ef76cc8bf8bda4aa499fada"
    },
    {
        "标题": "久坐伤身？换个方式坐，反而排湿又养身",
        "链接": "http://mp.weixin.qq.com/s?__biz=MzAwNTc0Mzc2Ng==&mid=2651488525&idx=2&sn=ef37796c6d1a5ee62dafce808ef47ff9"
    },
    {
        "标题": "西游记中金池长老只是个凡人，为何能活到270岁？你看他跟谁玩",
        "链接": "http://mp.weixin.qq.com/s?__biz=MzAwNTc0Mzc2Ng==&mid=2651488525&idx=3&sn=2f5d47be9af72001bd7f4318cd7acb58"
    },
    {
        "标题": "明朝第5位皇帝朱瞻基，身上存在不少谜团，600年来始终无解",
        "链接": "http://mp.weixin.qq.com/s?__biz=MzAwNTc0Mzc2Ng==&mid=2651488446&idx=1&sn=319ecbbb1e1dfa3fe2e498cbd933261b"
    },
    {
        "标题": "历史上最流氓的姓氏，读起来像是在骂人，但却是一代枭雄后代",
        "链接": "http://mp.weixin.qq.com/s?__biz=MzAwNTc0Mzc2Ng==&mid=2651488446&idx=2&sn=d304cae23b0c61c5457d794345ab3ce2"
    },
    {
        "标题": "二战纳粹第一女魔头，别看长的漂亮，对少妇心狠手辣！胸大就得死！",
        "链接": "http://mp.weixin.qq.com/s?__biz=MzAwNTc0Mzc2Ng==&mid=2651488434&idx=1&sn=9e0d7382c46b74b886c9f9756c3c74cd"
    },
    {
        "标题": "唐僧竟然还有一个弟子比孙悟空更传奇",
        "链接": "http://mp.weixin.qq.com/s?__biz=MzAwNTc0Mzc2Ng==&mid=2651488434&idx=2&sn=7bdd73f79f1cabd80379a88d073b56b2"
    },
    {
        "标题": "皇帝批奏章到深夜，宫女端来一碗热粥，皇帝：粥留下，人斩了",
        "链接": "http://mp.weixin.qq.com/s?__biz=MzAwNTc0Mzc2Ng==&mid=2651488419&idx=1&sn=3dea38ec48a8c067c2c714a5554f6139"
    },
    {
        "标题": "心疼女人的男人是怎样？看杜月笙如何对孟小冬这一个举动就知道！",
        "链接": "http://mp.weixin.qq.com/s?__biz=MzAwNTc0Mzc2Ng==&mid=2651488412&idx=1&sn=486a049352532f530a9bfacf02bf102d"
    },
    {
        "标题": "戴笠向胡蝶求婚，胡蝶说自己已有丈夫，戴笠笑道：我已经安排他去享福了",
        "链接": "http://mp.weixin.qq.com/s?__biz=MzAwNTc0Mzc2Ng==&mid=2651488403&idx=1&sn=393925319ba9f432a538a1509a4e144c"
    },
    {
        "标题": "大宅门里的丫鬟香秀原型竟是她？难怪一路开挂似的",
        "链接": "http://mp.weixin.qq.com/s?__biz=MzAwNTc0Mzc2Ng==&mid=2651488403&idx=2&sn=23941db634eb780304ddc83f355f457f"
    },
    {
        "标题": "两女儿同时被封妃，母亲不喜反悲：妹妹入宫必死，多年后应验",
        "链接": "http://mp.weixin.qq.com/s?__biz=MzAwNTc0Mzc2Ng==&mid=2651488393&idx=1&sn=3c5dddcde02f4befe09b27bdb4040a46"
    },
    {
        "标题": "比跑鞋软，比凉鞋凉！雨天“淋不湿”的空调鞋，舒服到起飞，一口气买了三双~",
        "链接": "http://mp.weixin.qq.com/s?__biz=MzAwNTc0Mzc2Ng==&mid=2651488393&idx=3&sn=13a030447a3ed0f3d0ef396a97f8c534"
    },
    {
        "标题": "才女出一上联：“王不出头谁做主”，才子下联如何优雅地怼回去",
        "链接": "http://mp.weixin.qq.com/s?__biz=MzAwNTc0Mzc2Ng==&mid=2651488393&idx=4&sn=4ee8f74aa03ec5af82f55d2473cb9a20"
    },
    {
        "标题": "数万人打出9.4分，它比《长安三万里》后劲还大！",
        "链接": "http://mp.weixin.qq.com/s?__biz=MzAwNTc0Mzc2Ng==&mid=2651488380&idx=2&sn=58fc4f82d72c1305193d928afc635887"
    },
    {
        "标题": "他娶了自己的亲外孙女，惹恼了孙子，却促成了一件大喜事",
        "链接": "http://mp.weixin.qq.com/s?__biz=MzAwNTc0Mzc2Ng==&mid=2651488380&idx=4&sn=2c284256b0aba26ea7f279da87a2c091"
    },
    {
        "标题": "陈圆圆究竟被多少个男人占有过？一个比一个来头大",
        "链接": "http://mp.weixin.qq.com/s?__biz=MzAwNTc0Mzc2Ng==&mid=2651488380&idx=1&sn=015667b3ba89a7c469a9943ddbd2aec8"
    },
    {
        "标题": "钱学森36岁没结婚，干妹妹给他介绍对象，钱学森：“要不你嫁给我吧”",
        "链接": "http://mp.weixin.qq.com/s?__biz=MzAwNTc0Mzc2Ng==&mid=2651488362&idx=1&sn=4cb440dde86ed8773ef4fb7f5820fbce"
    },
    {
        "标题": "关羽一生斩杀18员大将，唯独杀了这个人，后悔了一辈子",
        "链接": "http://mp.weixin.qq.com/s?__biz=MzAwNTc0Mzc2Ng==&mid=2651488362&idx=4&sn=6a18871ae5676138773e37eaae560144"
    },
    {
        "标题": "他本高中状元，慈禧看到名字却说：取消成绩，没想后来推翻了清朝",
        "链接": "http://mp.weixin.qq.com/s?__biz=MzAwNTc0Mzc2Ng==&mid=2651488330&idx=1&sn=c2ac746607b701f1c98f0f839ec1c4c6"
    },
    {
        "标题": "幽州到底是个什么地方？为何总发生叛乱？真是英雄所见略同",
        "链接": "http://mp.weixin.qq.com/s?__biz=MzAwNTc0Mzc2Ng==&mid=2651488330&idx=4&sn=ce8bf3c3d3b354ca5a482a97b38c5031"
    },
    {
        "标题": "观音菩萨的智慧谋略：将无意义转化为有意义，你就是人生大赢家",
        "链接": "http://mp.weixin.qq.com/s?__biz=MzAwNTc0Mzc2Ng==&mid=2651488327&idx=1&sn=e3d042460e8224b26dce140aea424356"
    },
    {
        "标题": "数万人打出9.4分，它比《长安三万里》后劲还大！",
        "链接": "http://mp.weixin.qq.com/s?__biz=MzAwNTc0Mzc2Ng==&mid=2651488327&idx=2&sn=745251960275913020c969cd0c7207f1"
    },
    {
        "标题": "牛仔裤下岗了！今年流行“空调神仙裤”，穿上立降5℃，透气不粘腿，双腿又直又长！走起路来都带风！",
        "链接": "http://mp.weixin.qq.com/s?__biz=MzAwNTc0Mzc2Ng==&mid=2651488327&idx=3&sn=991c849a62ef0e8bb0f43fd9161adb68"
    },
    {
        "标题": "他一连问了皇帝八句话，皇帝终于明白谁是奸臣了",
        "链接": "http://mp.weixin.qq.com/s?__biz=MzAwNTc0Mzc2Ng==&mid=2651488327&idx=4&sn=80dfe41950d8a47f5a8a13141c5816b8"
    },
    {
        "标题": "动物阉割只割蛋蛋，为何太监连“鸟儿”都不放过",
        "链接": "http://mp.weixin.qq.com/s?__biz=MzAwNTc0Mzc2Ng==&mid=2651488315&idx=1&sn=523a3578189e2b2c4df873d49e669622"
    },
    {
        "标题": "坐着体内寒气就没了，这种500年前的养生方法，老中医都服气",
        "链接": "http://mp.weixin.qq.com/s?__biz=MzAwNTc0Mzc2Ng==&mid=2651488315&idx=2&sn=df69573654072198ca340c0fa84377e8"
    },
    {
        "标题": "牙刷怎样选？小编试用完被狠狠种草...（好用不贵）",
        "链接": "http://mp.weixin.qq.com/s?__biz=MzAwNTc0Mzc2Ng==&mid=2651488315&idx=3&sn=9a3dc973f0e51f16b82a535f8f97468e"
    },
    {
        "标题": "帝王终结者，他连灭六个皇帝，后来他自己做了皇帝",
        "链接": "http://mp.weixin.qq.com/s?__biz=MzAwNTc0Mzc2Ng==&mid=2651488315&idx=4&sn=35a231f8e17099932a4cbdcae1fe725b"
    },
    {
        "标题": "因名字太过高雅，校长嫌弃，改了个土名字，结果成家喻户晓的女星",
        "链接": "http://mp.weixin.qq.com/s?__biz=MzAwNTc0Mzc2Ng==&mid=2651488278&idx=1&sn=e7b60844be0e7c3240bdbf3aa57a130c"
    },
    {
        "标题": "他写透人性的情与欲，让王家卫、冯唐疯狂痴迷……",
        "链接": "http://mp.weixin.qq.com/s?__biz=MzAwNTc0Mzc2Ng==&mid=2651488278&idx=2&sn=aadcc8510fd2c0d85189fc92667e0cbf"
    },
    {
        "标题": "比跑鞋软，比凉鞋凉！雨天“淋不湿”的空调鞋，舒服到起飞，一口气买了三双~",
        "链接": "http://mp.weixin.qq.com/s?__biz=MzAwNTc0Mzc2Ng==&mid=2651488278&idx=3&sn=936f80e254e0a468d936ba8c7b0a645d"
    },
    {
        "标题": "唐玄宗究竟是怎样从一代明君跌入万丈深渊的",
        "链接": "http://mp.weixin.qq.com/s?__biz=MzAwNTc0Mzc2Ng==&mid=2651488278&idx=4&sn=1af7e4f33ee37170803a7f7ea2d93e29"
    },
    {
        "标题": "苏联俘虏60万关东军，押到战俘营服劳役，为何日军最怕苏联女护士",
        "链接": "http://mp.weixin.qq.com/s?__biz=MzAwNTc0Mzc2Ng==&mid=2651488266&idx=1&sn=68c5546b84b5440314578cb1875904ab"
    },
    {
        "标题": "坐着体内寒气就没了，这种500年前的养生方法，老中医都服气",
        "链接": "http://mp.weixin.qq.com/s?__biz=MzAwNTc0Mzc2Ng==&mid=2651488266&idx=2&sn=aa1c9773db2d493a8835e809143a9982"
    },
    {
        "标题": "停印多年，终于重出江湖！",
        "链接": "http://mp.weixin.qq.com/s?__biz=MzAwNTc0Mzc2Ng==&mid=2651488266&idx=3&sn=06c0ab76b726f8c61baf621d18f9b472"
    },
    {
        "标题": "唐僧通关文牒上竟然有狮驼国的印章？给他盖章的是谁？",
        "链接": "http://mp.weixin.qq.com/s?__biz=MzAwNTc0Mzc2Ng==&mid=2651488266&idx=4&sn=d120061beca03941d802e24e98ae3e90"
    },
    {
        "标题": "知府、道台、封疆大吏、提督、总督、巡抚都是什么官？谁的官职最大",
        "链接": "http://mp.weixin.qq.com/s?__biz=MzAwNTc0Mzc2Ng==&mid=2651488265&idx=1&sn=4080f8ae747a5e18d921a2229d662de6"
    },
    {
        "标题": "数万人打出9.4分，它比《长安三万里》后劲还大！",
        "链接": "http://mp.weixin.qq.com/s?__biz=MzAwNTc0Mzc2Ng==&mid=2651488265&idx=2&sn=77a3f0bb9fc0d6fcc5ee45ccde93c206"
    },
    {
        "标题": "久坐伤腰屁股大，这款矫正坐垫，保护腰尾椎，翘臀“坐”出来",
        "链接": "http://mp.weixin.qq.com/s?__biz=MzAwNTc0Mzc2Ng==&mid=2651488265&idx=3&sn=ad8e36ee576f635acf7dee89b3dedaaa"
    },
    {
        "标题": "乾隆太过精明，为何把资质平庸的嘉庆确立为接班人",
        "链接": "http://mp.weixin.qq.com/s?__biz=MzAwNTc0Mzc2Ng==&mid=2651488265&idx=4&sn=3b75d4554c35080997b39ac345ba4631"
    },
    {
        "标题": "金庸笔下的八大蠢人，专练三流武功，最终把自己都练废了",
        "链接": "http://mp.weixin.qq.com/s?__biz=MzAwNTc0Mzc2Ng==&mid=2651488245&idx=1&sn=954552c599d5775a968f65e3cdb64e84"
    },
    {
        "标题": "坐着体内寒气就没了，这种500年前的养生方法，老中医都服气",
        "链接": "http://mp.weixin.qq.com/s?__biz=MzAwNTc0Mzc2Ng==&mid=2651488245&idx=2&sn=22ebdec3b9b675fe846c9bec95883388"
    },
    {
        "标题": "“会变身”的旅行包，可大可小，巨能装，还防 水，出门超实用！",
        "链接": "http://mp.weixin.qq.com/s?__biz=MzAwNTc0Mzc2Ng==&mid=2651488245&idx=3&sn=355862cf9e14d595a41e5de123894a0b"
    },
    {
        "标题": "黄巢兵败被杀后，唐僖宗是怎么对待他的妻妾的？",
        "链接": "http://mp.weixin.qq.com/s?__biz=MzAwNTc0Mzc2Ng==&mid=2651488245&idx=4&sn=b0b89d4ce700221fbe7408535b1e807c"
    },
    {
        "标题": "戚夫人被折磨成“人彘”后活了多久？",
        "链接": "http://mp.weixin.qq.com/s?__biz=MzAwNTc0Mzc2Ng==&mid=2651488238&idx=1&sn=284bda175901bceefadbbb00bdacf3c9"
    },
    {
        "标题": "数万人打出9.4分，它比《长安三万里》后劲还大！",
        "链接": "http://mp.weixin.qq.com/s?__biz=MzAwNTc0Mzc2Ng==&mid=2651488238&idx=2&sn=a03c5ee51c6aba45700be92fa288393b"
    },
    {
        "标题": "比跑鞋软，比凉鞋凉！雨天“淋不湿”的空调鞋，舒服到起飞，一口气买了三双~",
        "链接": "http://mp.weixin.qq.com/s?__biz=MzAwNTc0Mzc2Ng==&mid=2651488238&idx=3&sn=9d8fc68a9d7111c3bd1dde6076a4306f"
    },
    {
        "标题": "原来你一直喝的是货币、药物、饮用水、马尿，今天给你揭露真相",
        "链接": "http://mp.weixin.qq.com/s?__biz=MzAwNTc0Mzc2Ng==&mid=2651488238&idx=4&sn=ee84d6cab7de66aa633ed3f12a317641"
    },
    {
        "标题": "孙悟空修为是何境界？为何自称天生圣人？菩提祖师一语道破天机",
        "链接": "http://mp.weixin.qq.com/s?__biz=MzAwNTc0Mzc2Ng==&mid=2651488186&idx=1&sn=d446879c07d7bbc5aa41d090abd0a7c4"
    },
    {
        "标题": "坐着体内寒气就没了，这种500年前的养生方法，老中医都服气",
        "链接": "http://mp.weixin.qq.com/s?__biz=MzAwNTc0Mzc2Ng==&mid=2651488186&idx=2&sn=53bec3d6e0b16209c0035424881c7270"
    },
    {
        "标题": "久坐伤腰屁股大，这款矫正坐垫，保护腰尾椎，翘臀“坐”出来",
        "链接": "http://mp.weixin.qq.com/s?__biz=MzAwNTc0Mzc2Ng==&mid=2651488186&idx=3&sn=56ecc22617bd4849d778f6fa885d891e"
    },
    {
        "标题": "将军战前分肉给士兵吃，唯独没分给自己的车夫，第二天交战时…",
        "链接": "http://mp.weixin.qq.com/s?__biz=MzAwNTc0Mzc2Ng==&mid=2651488186&idx=4&sn=0c6c55d864ba9be54b888e4d07b97a28"
    },
    {
        "标题": "妲己睡前有个坏习惯，纣王迷得神魂颠倒，现代女孩都不敢这么做",
        "链接": "http://mp.weixin.qq.com/s?__biz=MzAwNTc0Mzc2Ng==&mid=2651488183&idx=1&sn=8c4f8042a1200624910642e36d2e8340"
    },
    {
        "标题": "坐着体内寒气就没了，这种500年前的养生方法，老中医都服气",
        "链接": "http://mp.weixin.qq.com/s?__biz=MzAwNTc0Mzc2Ng==&mid=2651488183&idx=2&sn=7b293327f9c1b7ad230ec49b40d3d7a2"
    },
    {
        "标题": "豆瓣9.7！要不是这套书，我就是另外一个人了……",
        "链接": "http://mp.weixin.qq.com/s?__biz=MzAwNTc0Mzc2Ng==&mid=2651488183&idx=3&sn=4989fc69a6e62708f7200e34a5ec4067"
    },
    {
        "标题": "大明虐她千百遍，她待大明如初恋",
        "链接": "http://mp.weixin.qq.com/s?__biz=MzAwNTc0Mzc2Ng==&mid=2651488183&idx=4&sn=ed3020f8ad45f1585c17f3393ac04a01"
    },
    {
        "标题": "为何猪八戒吃人参果时要整颗吞下，只因他知道其中的秘密",
        "链接": "http://mp.weixin.qq.com/s?__biz=MzAwNTc0Mzc2Ng==&mid=2651488152&idx=1&sn=e3480c95f18d9afcb81ee1d87cac6109"
    },
    {
        "标题": "《水浒传》中被忽略的小人物，如果没有他，十个鲁智深也救不了林教头",
        "链接": "http://mp.weixin.qq.com/s?__biz=MzAwNTc0Mzc2Ng==&mid=2651488152&idx=4&sn=0cbf7e1239d9cea6517edc2e115af44d"
    },
    {
        "标题": "男人过了多少岁，对女人不再心动？心理学家的答案很统一",
        "链接": "http://mp.weixin.qq.com/s?__biz=MzAwNTc0Mzc2Ng==&mid=2651488109&idx=1&sn=53022e28e4a893c524a488a5d7c2d17e"
    },
    {
        "标题": "久坐伤腰屁股大，这款矫正坐垫，保护腰尾椎，翘臀“坐”出来",
        "链接": "http://mp.weixin.qq.com/s?__biz=MzAwNTc0Mzc2Ng==&mid=2651488109&idx=2&sn=a0c7311e39d96fa183623e084b737153"
    },
    {
        "标题": "为什么关羽必须死，背后的真相令人震惊",
        "链接": "http://mp.weixin.qq.com/s?__biz=MzAwNTc0Mzc2Ng==&mid=2651488109&idx=3&sn=9900be6145ace1ef45aa76ef2d2a9ac6"
    },
    {
        "标题": "乾隆出一上联：鼠无大小皆称老，纪晓岚对出的下联堪称千古绝对",
        "链接": "http://mp.weixin.qq.com/s?__biz=MzAwNTc0Mzc2Ng==&mid=2651488100&idx=1&sn=b4457e038b6179003d0f333a987cd31a"
    },
    {
        "标题": "坐着体内寒气就没了，这种500年前的养生方法，老中医都服气",
        "链接": "http://mp.weixin.qq.com/s?__biz=MzAwNTc0Mzc2Ng==&mid=2651488100&idx=2&sn=c2cf498f705bdbabfc2e22dd0b31f508"
    },
    {
        "标题": "为何唐僧悟空都成佛，观音却还是菩萨，观音原来不是如来的人",
        "链接": "http://mp.weixin.qq.com/s?__biz=MzAwNTc0Mzc2Ng==&mid=2651488100&idx=3&sn=9d2846613fd6c9cf8dd0ed78673abcbc"
    },
    {
        "标题": "黄蓉为何讨厌杨过？你看她与杨过抱在一起时想到啥？",
        "链接": "http://mp.weixin.qq.com/s?__biz=MzAwNTc0Mzc2Ng==&mid=2651488090&idx=1&sn=48054cbf0ea0d47e53a4430b32b2f168"
    },
    {
        "标题": "看鬼谷子与骊山老母如何从《战国七雄争霸》玩到《楚汉热血传奇》",
        "链接": "http://mp.weixin.qq.com/s?__biz=MzAwNTc0Mzc2Ng==&mid=2651488090&idx=5&sn=62a3b138195ec88e0ef31f2df26871cd"
    },
    {
        "标题": "这是故宫里，最诡异的一幅古籍画，还隐藏了一个恐怖故事",
        "链接": "http://mp.weixin.qq.com/s?__biz=MzAwNTc0Mzc2Ng==&mid=2651488055&idx=1&sn=5cf58b4f68c58bd31462133e04b14260"
    },
    {
        "标题": "百万军中取上将首级的王者，历史上真有这么一个人",
        "链接": "http://mp.weixin.qq.com/s?__biz=MzAwNTc0Mzc2Ng==&mid=2651488055&idx=4&sn=1e8744ca40454497a9c8b51fcae44ceb"
    },
    {
        "标题": "金圣叹被斩首后，耳朵里掉出两块纸团，一个写着好，一个写着疼",
        "链接": "http://mp.weixin.qq.com/s?__biz=MzAwNTc0Mzc2Ng==&mid=2651488054&idx=1&sn=629d7ba140a4dc2b8a51a310b051b0bc"
    },
    {
        "标题": "历史上被使用次数最多的国号，竟然有二十一次之多",
        "链接": "http://mp.weixin.qq.com/s?__biz=MzAwNTc0Mzc2Ng==&mid=2651488054&idx=4&sn=72e9b8d2119dd5242919e88dcdcad29e"
    },
    {
        "标题": "明朝奇人王世宁活了128岁，一生只吃两样东西，现在很少有人吃了",
        "链接": "http://mp.weixin.qq.com/s?__biz=MzAwNTc0Mzc2Ng==&mid=2651488053&idx=1&sn=4f9f2ce5e1c55a1a75b91c22a7a4d520"
    },
    {
        "标题": "坐着体内寒气就没了，这种500年前的养生方法，老中医都服气",
        "链接": "http://mp.weixin.qq.com/s?__biz=MzAwNTc0Mzc2Ng==&mid=2651488053&idx=2&sn=1e67170ac824bfd89bb9848e61e67fa6"
    },
    {
        "标题": "“会变身”的旅行包，可大可小，巨能装，还防 水，出门超实用！",
        "链接": "http://mp.weixin.qq.com/s?__biz=MzAwNTc0Mzc2Ng==&mid=2651488053&idx=3&sn=4986ab9ff818ecc0bee154101e79f027"
    },
    {
        "标题": "诡异的饭局：皇帝赐宴却不给筷子，重用或赐死就在这一刻决定",
        "链接": "http://mp.weixin.qq.com/s?__biz=MzAwNTc0Mzc2Ng==&mid=2651488053&idx=4&sn=6e5d7c0347e83ab1513cc9fe01809929"
    },
    {
        "标题": "皇帝宴请弟弟，倒杯毒酒说：祝弟弟活千岁，弟弟一个动作保住性命",
        "链接": "http://mp.weixin.qq.com/s?__biz=MzAwNTc0Mzc2Ng==&mid=2651488050&idx=1&sn=906913f6158f70b51740ded7491693b0"
    },
    {
        "标题": "坐着体内寒气就没了，这种500年前的养生方法，老中医都服气",
        "链接": "http://mp.weixin.qq.com/s?__biz=MzAwNTc0Mzc2Ng==&mid=2651488050&idx=2&sn=d51b9d6ff90761a9b13229f37a474431"
    },
    {
        "标题": "比跑鞋软，比凉鞋凉！雨天“淋不湿”的空调鞋，舒服到起飞，一口气买了三双~",
        "链接": "http://mp.weixin.qq.com/s?__biz=MzAwNTc0Mzc2Ng==&mid=2651488050&idx=3&sn=ee178d3fb8e36d8409d887733d7a3700"
    },
    {
        "标题": "林黛玉究竟有多美，薛蟠只瞥了她一眼，瞬间被酥倒",
        "链接": "http://mp.weixin.qq.com/s?__biz=MzAwNTc0Mzc2Ng==&mid=2651488050&idx=4&sn=c9bd62be10fce6df6937a35d1485737e"
    },
    {
        "标题": "俗语“寡妇三更磨豆腐，光棍半夜洗衣服”，寡妇为何熬夜磨豆腐？",
        "链接": "http://mp.weixin.qq.com/s?__biz=MzAwNTc0Mzc2Ng==&mid=2651488049&idx=1&sn=207abe1c3804daad33a33408d15affa6"
    },
    {
        "标题": "坐着体内寒气就没了，这种500年前的养生方法，老中医都服气",
        "链接": "http://mp.weixin.qq.com/s?__biz=MzAwNTc0Mzc2Ng==&mid=2651488049&idx=2&sn=94a32d915f4bb17442fd055bc246843c"
    },
    {
        "标题": "豆瓣9.7！要不是这套书，我就是另外一个人了……",
        "链接": "http://mp.weixin.qq.com/s?__biz=MzAwNTc0Mzc2Ng==&mid=2651488049&idx=3&sn=375892be4abb6efbac722882cedba4b8"
    },
    {
        "标题": "冲冠一怒为婶娘，你不知道的三国历史",
        "链接": "http://mp.weixin.qq.com/s?__biz=MzAwNTc0Mzc2Ng==&mid=2651488049&idx=4&sn=da5f39ed9e77ec69cc82df1041b7a68b"
    },
    {
        "标题": "宝玉和袭人相好多年，她为何一直没有身孕？黛玉无意间道出真相",
        "链接": "http://mp.weixin.qq.com/s?__biz=MzAwNTc0Mzc2Ng==&mid=2651488048&idx=1&sn=1811d24aa83c5a506fa0b19a406c66c4"
    },
    {
        "标题": "坐着体内寒气就没了，这种500年前的养生方法，老中医都服气",
        "链接": "http://mp.weixin.qq.com/s?__biz=MzAwNTc0Mzc2Ng==&mid=2651488048&idx=2&sn=6c7870698aa33630c230640ffc881822"
    },
    {
        "标题": "“绝望的文盲”上热搜：比文盲更可怕的是不懂历史！",
        "链接": "http://mp.weixin.qq.com/s?__biz=MzAwNTc0Mzc2Ng==&mid=2651488048&idx=3&sn=e11ebd247c481a20063fb36283692f5f"
    },
    {
        "标题": "古代没有DNA技术，居然还有3种方法做亲子鉴定",
        "链接": "http://mp.weixin.qq.com/s?__biz=MzAwNTc0Mzc2Ng==&mid=2651488048&idx=4&sn=edc5a244895dca0a0ef3b6e235ab395b"
    },
    {
        "标题": "崇祯的最后十二时辰，帝国毁灭前夜，崇祯竟对家人大开杀戒",
        "链接": "http://mp.weixin.qq.com/s?__biz=MzAwNTc0Mzc2Ng==&mid=2651488047&idx=1&sn=6aab45aa0af47eddd567a4e822e87d98"
    },
    {
        "标题": "坐着体内寒气就没了，这种500年前的养生方法，老中医都服气",
        "链接": "http://mp.weixin.qq.com/s?__biz=MzAwNTc0Mzc2Ng==&mid=2651488047&idx=2&sn=ed9882242ae99983d017fb19c97dbca2"
    },
    {
        "标题": "“会变身”的旅行包，可大可小，巨能装，还防 水，出门超实用！",
        "链接": "http://mp.weixin.qq.com/s?__biz=MzAwNTc0Mzc2Ng==&mid=2651488047&idx=3&sn=19f6c70926f5a25a059903e5a6d75f38"
    },
    {
        "标题": "宋江：遇到能为我所用的猛将，就跪了",
        "链接": "http://mp.weixin.qq.com/s?__biz=MzAwNTc0Mzc2Ng==&mid=2651488047&idx=4&sn=4b9c3775e9a90971e75f936d06407a36"
    },
    {
        "标题": "古代老人60岁就被关进墓穴，吃一餐加一砖，活活等死，瓦罐坟有多残忍？",
        "链接": "http://mp.weixin.qq.com/s?__biz=MzAwNTc0Mzc2Ng==&mid=2651488043&idx=1&sn=829f5aedf884861356c305392bd1c1fa"
    },
    {
        "标题": "坐着体内寒气就没了，这种500年前的养生方法，老中医都服气",
        "链接": "http://mp.weixin.qq.com/s?__biz=MzAwNTc0Mzc2Ng==&mid=2651488043&idx=2&sn=4c04b614c47be7b0102a1f288aec45d4"
    },
    {
        "标题": "停印多年，终于重出江湖！",
        "链接": "http://mp.weixin.qq.com/s?__biz=MzAwNTc0Mzc2Ng==&mid=2651488043&idx=3&sn=3797c4192babc94de851967455082672"
    },
    {
        "标题": "这个王朝覆亡后，皇室男女被迫近亲婚配，结果仍被灭族",
        "链接": "http://mp.weixin.qq.com/s?__biz=MzAwNTc0Mzc2Ng==&mid=2651488043&idx=4&sn=4e3ff5dfc4117bb1fdb50c30a9370c53"
    },
    {
        "标题": "奎木狼、沙僧下凡都不用投胎，为何只有猪八戒投了猪胎？",
        "链接": "http://mp.weixin.qq.com/s?__biz=MzAwNTc0Mzc2Ng==&mid=2651488040&idx=1&sn=ae6bd9759bd6bca51c55de86cdc859ae"
    },
    {
        "标题": "比跑鞋软，比凉鞋凉！雨天“淋不湿”的空调鞋，舒服到起飞，一口气买了三双~",
        "链接": "http://mp.weixin.qq.com/s?__biz=MzAwNTc0Mzc2Ng==&mid=2651488040&idx=2&sn=e8752d4f719d91d166443c77b0edfe41"
    },
    {
        "标题": "别在“臭水沟”里洗衣服了！教你一招，排出10斤黑脏水，天天都用新的洗衣机~",
        "链接": "http://mp.weixin.qq.com/s?__biz=MzAwNTc0Mzc2Ng==&mid=2651488040&idx=3&sn=6972eb42e0a593794fcd377cfdacc4f7"
    },
    {
        "标题": "“宁肯夜宿荒坟，不可夜居古庙”，有多可怕？能比鬼还吓人吗？",
        "链接": "http://mp.weixin.qq.com/s?__biz=MzAwNTc0Mzc2Ng==&mid=2651488040&idx=4&sn=c1f5976d24fb587891533f378d03b319"
    },
    {
        "标题": "他是郭靖的师傅，更让傲娇的成吉思汗甘拜下风",
        "链接": "http://mp.weixin.qq.com/s?__biz=MzAwNTc0Mzc2Ng==&mid=2651488040&idx=5&sn=238d4bf0f9b7ad85c65aaf8e492a3524"
    },
    {
        "标题": "为什么算命先生不认识你，却知道你家几口人？内行人揭秘骗局",
        "链接": "http://mp.weixin.qq.com/s?__biz=MzAwNTc0Mzc2Ng==&mid=2651488024&idx=1&sn=fbc39555d8c73849af454dde58335581"
    },
    {
        "标题": "坐着体内寒气就没了，这种500年前的养生方法，老中医都服气",
        "链接": "http://mp.weixin.qq.com/s?__biz=MzAwNTc0Mzc2Ng==&mid=2651488024&idx=2&sn=bd19c4990aa4f7ebca4864bc7f19fc82"
    },
    {
        "标题": "“会变身”的旅行包，可大可小，巨能装，还防 水，出门超实用！",
        "链接": "http://mp.weixin.qq.com/s?__biz=MzAwNTc0Mzc2Ng==&mid=2651488024&idx=3&sn=e40896002250ddc9a576181f22d47221"
    },
    {
        "标题": "有一个暴君，他的后宫美女竟超过十万，他是谁",
        "链接": "http://mp.weixin.qq.com/s?__biz=MzAwNTc0Mzc2Ng==&mid=2651488024&idx=4&sn=ecd59df175f8e51970620ae275c345dd"
    },
    {
        "标题": "他武功盖世曾名震四方，上梁山后从不上阵打仗，宋江都指挥不动他",
        "链接": "http://mp.weixin.qq.com/s?__biz=MzAwNTc0Mzc2Ng==&mid=2651488021&idx=1&sn=050699c1b9da9e47e90ded7d258d0948"
    },
    {
        "标题": "坐着体内寒气就没了，这种500年前的养生方法，老中医都服气",
        "链接": "http://mp.weixin.qq.com/s?__biz=MzAwNTc0Mzc2Ng==&mid=2651488021&idx=2&sn=c2d6510fef83d7cfed8d48a182683eb7"
    },
    {
        "标题": "豆瓣9.7！要不是这套书，我就是另外一个人了……",
        "链接": "http://mp.weixin.qq.com/s?__biz=MzAwNTc0Mzc2Ng==&mid=2651488021&idx=3&sn=153368dcd5a0b3ec4f8260589417bcb4"
    },
    {
        "标题": "曹丕将妻子甄宓赐死后，为何还要在她的嘴里塞满污秽之物？",
        "链接": "http://mp.weixin.qq.com/s?__biz=MzAwNTc0Mzc2Ng==&mid=2651488021&idx=4&sn=6e72acbce63c39dbb1602b19b6f3b35c"
    },
    {
        "标题": "非洲神秘部落：嘴唇上装盘子的女人，盘子的尺寸越大，收到的彩礼就越多",
        "链接": "http://mp.weixin.qq.com/s?__biz=MzAwNTc0Mzc2Ng==&mid=2651488017&idx=1&sn=bb70375fdbc3c752f210f59a6fb21b05"
    },
    {
        "标题": "坐着体内寒气就没了，这种500年前的养生方法，老中医都服气",
        "链接": "http://mp.weixin.qq.com/s?__biz=MzAwNTc0Mzc2Ng==&mid=2651488017&idx=2&sn=4e2b9d18f3091a25e83fb36c4dcb1869"
    },
    {
        "标题": "“会变身”的旅行包，可大可小，巨能装，还防 水，出门超实用！",
        "链接": "http://mp.weixin.qq.com/s?__biz=MzAwNTc0Mzc2Ng==&mid=2651488017&idx=3&sn=9752185723d36265c9c1ef5828b9d987"
    },
    {
        "标题": "古代第一女神相对西汉战神周亚夫的神预言",
        "链接": "http://mp.weixin.qq.com/s?__biz=MzAwNTc0Mzc2Ng==&mid=2651488017&idx=4&sn=0d537e17de85410c50d5dd34a4a369f5"
    },
    {
        "标题": "有野心的穷人，没钱没人脉，牢记曾国藩4字真言，助你飞黄腾达",
        "链接": "http://mp.weixin.qq.com/s?__biz=MzAwNTc0Mzc2Ng==&mid=2651488014&idx=1&sn=e496ccedf0e2fa69079fe5f3d40e2c0e"
    },
    {
        "标题": "“绝望的文盲”上热搜：比文盲更可怕的是不懂历史！",
        "链接": "http://mp.weixin.qq.com/s?__biz=MzAwNTc0Mzc2Ng==&mid=2651488014&idx=2&sn=a77384de873856eb564f8b3551074493"
    },
    {
        "标题": "“吓跑”蚊子！触手生凉！夏天躺在“它”身上睡觉竟然这么爽！",
        "链接": "http://mp.weixin.qq.com/s?__biz=MzAwNTc0Mzc2Ng==&mid=2651488014&idx=3&sn=3de8af051d78d1daef1f498876d948d3"
    },
    {
        "标题": "此人称帝后，把自家妻妾掉了个，也把父亲的妻妾掉了个",
        "链接": "http://mp.weixin.qq.com/s?__biz=MzAwNTc0Mzc2Ng==&mid=2651488014&idx=4&sn=eac9e64bfc2817ecbce953c9a17ca440"
    },
    {
        "标题": "古埃及金字塔的神秘诅咒，传言进入者必亡，到底是怎么一回事",
        "链接": "http://mp.weixin.qq.com/s?__biz=MzAwNTc0Mzc2Ng==&mid=2651487987&idx=1&sn=abac6b2a69067041a6f960c1d3d04139"
    },
    {
        "标题": "坐着体内寒气就没了，这种500年前的养生方法，老中医都服气",
        "链接": "http://mp.weixin.qq.com/s?__biz=MzAwNTc0Mzc2Ng==&mid=2651487987&idx=2&sn=3132ca1f2f74781b5d7ad8041753647e"
    },
    {
        "标题": "“会变身”的旅行包，可大可小，巨能装，还防 水，出门超实用！",
        "链接": "http://mp.weixin.qq.com/s?__biz=MzAwNTc0Mzc2Ng==&mid=2651487987&idx=3&sn=47fcbb9c2d5bcbd1ba48fa5ef9e6740c"
    },
    {
        "标题": "为什么林冲会是逼上梁山第一人",
        "链接": "http://mp.weixin.qq.com/s?__biz=MzAwNTc0Mzc2Ng==&mid=2651487987&idx=4&sn=5898b5e7fabf7d4c2fd0454b13477424"
    },
    {
        "标题": "吃人魔朱粲将爱妃煮了分给大臣，把百姓当军粮，20万军队得吃多少？",
        "链接": "http://mp.weixin.qq.com/s?__biz=MzAwNTc0Mzc2Ng==&mid=2651487917&idx=1&sn=fafde1649885d3a01a4f6cde28aef891"
    },
    {
        "标题": "久坐伤腰屁股大，这款人体工学坐垫，护腰又美臀！",
        "链接": "http://mp.weixin.qq.com/s?__biz=MzAwNTc0Mzc2Ng==&mid=2651487917&idx=2&sn=56cfdbc659c3b32ea7c62885f89e9838"
    },
    {
        "标题": "别在“臭水沟”里洗衣服了！教你一招，排出10斤黑脏水，天天都用新的洗衣机~",
        "链接": "http://mp.weixin.qq.com/s?__biz=MzAwNTc0Mzc2Ng==&mid=2651487917&idx=3&sn=20250e4a2d89c659524786a8e2364517"
    },
    {
        "标题": "他俩斗诗，引爆了大唐朋友圈",
        "链接": "http://mp.weixin.qq.com/s?__biz=MzAwNTc0Mzc2Ng==&mid=2651487917&idx=4&sn=8c9c4a71d6263176ea467b0fbab81ecd"
    },
    {
        "标题": "孙悟空在车迟国连杀三个凡人，为何唐僧这次不念紧箍咒？",
        "链接": "http://mp.weixin.qq.com/s?__biz=MzAwNTc0Mzc2Ng==&mid=2651487916&idx=1&sn=0c90775fdb96ee8377ca23bda7612cb0"
    },
    {
        "标题": "老祖宗说“富不添丁，穷不添女”，到底是为什么？你咋看？",
        "链接": "http://mp.weixin.qq.com/s?__biz=MzAwNTc0Mzc2Ng==&mid=2651487916&idx=4&sn=fb5c6b885ecbb0faa9f1674cd670b3a3"
    },
    {
        "标题": "武则天退位之后痛斥狄仁杰，骗得我好苦，这都源于一个老头",
        "链接": "http://mp.weixin.qq.com/s?__biz=MzAwNTc0Mzc2Ng==&mid=2651487916&idx=6&sn=2608d250de11ff097b19f153fb11a934"
    },
    {
        "标题": "皇帝要到丞相家喝酒，被太监拼死阻拦，事后皇帝：下令丞相满门抄斩",
        "链接": "http://mp.weixin.qq.com/s?__biz=MzAwNTc0Mzc2Ng==&mid=2651487901&idx=1&sn=1aa042593e2c4093bf331997fcdc4232"
    },
    {
        "标题": "行刑当日，他破口大骂，武则天怕了，从此定下一个规矩",
        "链接": "http://mp.weixin.qq.com/s?__biz=MzAwNTc0Mzc2Ng==&mid=2651487901&idx=4&sn=075fafa4b2ea6305ab69578ebb466502"
    },
    {
        "标题": "皇帝私访，问茶叶多少钱1斤，店家说500文，回宫后3人被处斩",
        "链接": "http://mp.weixin.qq.com/s?__biz=MzAwNTc0Mzc2Ng==&mid=2651487847&idx=1&sn=0f251b0e0f7401ed4a3aa691335dbdfe"
    },
    {
        "标题": "腰不行这件事，可能真的不怪你！",
        "链接": "http://mp.weixin.qq.com/s?__biz=MzAwNTc0Mzc2Ng==&mid=2651487847&idx=2&sn=e532cea6ccc7ee7ae47c4508d7746d15"
    },
    {
        "标题": "停印多年，终于重出江湖！",
        "链接": "http://mp.weixin.qq.com/s?__biz=MzAwNTc0Mzc2Ng==&mid=2651487847&idx=3&sn=e86b96606bfc750df4b2d591f77ad8b7"
    },
    {
        "标题": "忘恩负义的小人贾雨村，为何却是林黛玉唯一的老师？看懂的人不多",
        "链接": "http://mp.weixin.qq.com/s?__biz=MzAwNTc0Mzc2Ng==&mid=2651487847&idx=4&sn=9f13b1aee2800323f25db344fe173c20"
    },
    {
        "标题": "武则天退位之后痛斥狄仁杰，骗得我好苦，这都源于一个老头",
        "链接": "http://mp.weixin.qq.com/s?__biz=MzAwNTc0Mzc2Ng==&mid=2651487840&idx=1&sn=597a2e55a4b3ce8066bb012d7bf51e71"
    }
]